CHANGELOG.txt
LICENSE.txt
MANIFEST.in
README.md
setup.py
lerpnet/__init__.py
lerpnet/autograd.py
lerpnet/layer.py
lerpnet/mlp.py
lerpnet/predictor.py
lerpnet/trainer.py
lerpnet/utils.py
lerpnet.egg-info/PKG-INFO
lerpnet.egg-info/SOURCES.txt
lerpnet.egg-info/dependency_links.txt
lerpnet.egg-info/requires.txt
lerpnet.egg-info/top_level.txt