Metadata-Version: 2.1
Name: lerpnet
Version: 1.0.2
Summary: Lightweight learnable interpolation using compact MLPs (edge & ESP32 ready)
Home-page: 
Author: Somendra Seth
Author-email: akhilresearch07@gmail.com
License: MIT
Keywords: machine-learning,interpolation,mlp,edge-ai,embedded,esp32,tinyml
Classifier: Development Status :: 5 - Production/Stable
Classifier: Intended Audience :: Developers
Classifier: Intended Audience :: Education
Classifier: License :: OSI Approved :: MIT License
Classifier: Operating System :: OS Independent
Classifier: Programming Language :: Python :: 3
Classifier: Programming Language :: Python :: 3 :: Only
Classifier: Topic :: Scientific/Engineering :: Artificial Intelligence
Classifier: Topic :: Software Development :: Embedded Systems
Requires-Python: >=3.8
License-File: LICENSE.txt
Requires-Dist: numpy
Requires-Dist: matplotlib
